earthquakealert_ID/__init__.py
earthquakealert_ID-0.0.6.dist-info/LICENSE
earthquakealert_ID-0.0.6.dist-info/METADATA
earthquakealert_ID-0.0.6.dist-info/WHEEL
earthquakealert_ID-0.0.6.dist-info/top_level.txt
earthquakealert_ID-0.0.6.dist-info/RECORD
