Metadata-Version: 2.1
Name: earthquakealert-ID
Version: 0.0.6
Summary: Retrieve latest earthquake alert from https://www.bmkg.go.id/
Home-page: https://github.com/ChristCoding/indonesian-earthquake-alert
Author: Christopher Lorence
Author-email: lorence80@gmail.com
License: UNKNOWN
Project-URL: Bug Tracker, https://github.com/ChristCoding/indonesian-earthquake-alert/issues
Platform: UNKNOWN
Classifier: Programming Language :: Python :: 3
Classifier: License :: OSI Approved :: GNU General Public License v3 (GPLv3)
Classifier: Operating System :: OS Independent
Classifier: Development Status :: 5 - Production/Stable
Requires-Python: >=3.6
License-File: LICENSE
